__init__.py
kv_text_to_speech/__init__.py
kv_text_to_speech/text_to_speech.py
kv_text_to_speech-0.1.0.dist-info/METADATA
kv_text_to_speech-0.1.0.dist-info/WHEEL
kv_text_to_speech-0.1.0.dist-info/top_level.txt
kv_text_to_speech-0.1.0.dist-info/RECORD
