Metadata-Version: 2.1
Name: kv-text-to-speech
Version: 0.1.0
Author-email: Justin Bui <jmbui@klangverso.com>
Requires-Python: >=3.8
Requires-Dist: azure-cognitiveservices-speech
